mstar/__init__.py
mstar/conf.py
mstar/mstar.py
mstar/plot.py
mstar/utils.py
mstar_alpha-0.0.2.dist-info/LICENSE
mstar_alpha-0.0.2.dist-info/METADATA
mstar_alpha-0.0.2.dist-info/WHEEL
mstar_alpha-0.0.2.dist-info/top_level.txt
mstar_alpha-0.0.2.dist-info/RECORD
