Metadata-Version: 2.1
Name: mstar-alpha
Version: 0.0.2
Summary: Stellar mass galaxy estimator
Home-page: https://mstar-alpha.readthedocs.io/en/
Author: Johnny Esteves
Author-email: jesteves@umich.edu
License: MIT License
Project-URL: readthedocs, https://mstar-alpha.readthedocs.io/
Project-URL: GitHub, https://github.com/estevesjh/mstar-alpha
Project-URL: arXiv, https://arxiv.org/
License-File: LICENSE
Requires-Dist: numpy
Requires-Dist: scikit-learn (>=0.22.1)
Requires-Dist: joblib
Requires-Dist: matplotlib
Requires-Dist: seaborn (>=0.10.1)
Requires-Dist: scipy (>=1.6.0)
Requires-Dist: pandas
